{
  "type": "Feature",
  "id": "lite.geologicunit.example1",
  "featureType": "LiteGeologicUnit",
  "conformsTo": [
    "https://schemas.usgin.org/geosci-json/geosciml_GeoSciMLLite/schema.json"
  ],
  "geometry": {
    "type": "Polygon",
    "coordinates": [
      [
        [
          -110.85,
          32.3
        ],
        [
          -110.8,
          32.3
        ],
        [
          -110.8,
          32.35
        ],
        [
          -110.85,
          32.35
        ],
        [
          -110.85,
          32.3
        ]
      ]
    ]
  },
  "properties": {
    "name": "Bolsa Quartzite (representative exposure)",
    "identifier": {
      "codeSpace": "http://resource.usgs.gov/stratigraphicLexicon",
      "value": "http://resource.usgs.gov/stratigraphicLexicon/6732"
    },
    "geologicUnitType": "http://resource.geosciml.org/classifier/cgi/geologicunittype/lithostratigraphic_unit",
    "representativeLithology": "http://resource.geosciml.org/classifier/cgi/simplelithology/quartzite",
    "representativeAge": "http://resource.geosciml.org/classifier/ics/ischart/Cambrian",
    "any": {
      "$comment": "GeoSciMLLite's open-content slot. Vendor-specific properties go here.",
      "ex:mappingScale": 100000,
      "ex:dataSource": "USGS Tucson 1:100,000 geologic map"
    }
  },
  "$comment": "Synthesised example of a LiteGeologicUnit — the GeoSciMLLite reduced encoding for simple feature consumers. The 'any' slot demonstrates the xs:any-equivalent extension point (lax wildcard in the source UML)."
}
